emojito/__init__.py
emojito/cli.py
emojito/core.py
emojito_py-0.2.0.dist-info/METADATA
emojito_py-0.2.0.dist-info/WHEEL
emojito_py-0.2.0.dist-info/entry_points.txt
emojito_py-0.2.0.dist-info/licenses/LICENSE
emojito_py-0.2.0.dist-info/RECORD
