Metadata-Version: 2.4
Name: emojito-py
Version: 0.2.0
Summary: Encode text into emojis using Unicode steganography
Project-URL: Homepage, https://github.com/matijaoe/emojito
Project-URL: Bug Tracker, https://github.com/matijaoe/emojito/issues
Project-URL: Repository, https://github.com/matijaoe/emojito.git
Author-email: Matija Osrečki <python@matijao.com>
License-Expression: MIT
License-File: LICENSE
Keywords: emoji,encoding,steganography,unicode
Classifier: License :: OSI Approved :: MIT License
Classifier: Operating System :: OS Independent
Classifier: Programming Language :: Python :: 3
Requires-Python: >=3.8
Provides-Extra: dev
Requires-Dist: pytest-cov>=4.0.0; extra == 'dev'
Requires-Dist: pytest>=7.0.0; extra == 'dev'
